pyp5js/__init__.py
pyp5js/cli.py
pyp5js/commands.py
pyp5js/compiler.py
pyp5js/exceptions.py
pyp5js/monitor.py
pyp5js/sketch.py
pyp5js/templates_renderers.py
pyp5js/config/__init__.py
pyp5js/config/fs.py
pyp5js/config/sketch.py
pyp5js/http_local/__init__.py
pyp5js/http_local/web_app.py
pyp5js/http_local/static/p5_reference.yml
pyp5js/http_local/static/js/ace/ace.js
pyp5js/http_local/static/js/ace/ext-beautify.js
pyp5js/http_local/static/js/ace/ext-code_lens.js
pyp5js/http_local/static/js/ace/ext-elastic_tabstops_lite.js
pyp5js/http_local/static/js/ace/ext-emmet.js
pyp5js/http_local/static/js/ace/ext-error_marker.js
pyp5js/http_local/static/js/ace/ext-keybinding_menu.js
pyp5js/http_local/static/js/ace/ext-language_tools.js
pyp5js/http_local/static/js/ace/ext-linking.js
pyp5js/http_local/static/js/ace/ext-modelist.js
pyp5js/http_local/static/js/ace/ext-options.js
pyp5js/http_local/static/js/ace/ext-prompt.js
pyp5js/http_local/static/js/ace/ext-rtl.js
pyp5js/http_local/static/js/ace/ext-searchbox.js
pyp5js/http_local/static/js/ace/ext-settings_menu.js
pyp5js/http_local/static/js/ace/ext-spellcheck.js
pyp5js/http_local/static/js/ace/ext-split.js
pyp5js/http_local/static/js/ace/ext-static_highlight.js
pyp5js/http_local/static/js/ace/ext-statusbar.js
pyp5js/http_local/static/js/ace/ext-textarea.js
pyp5js/http_local/static/js/ace/ext-themelist.js
pyp5js/http_local/static/js/ace/ext-whitespace.js
pyp5js/http_local/static/js/ace/keybinding-emacs.js
pyp5js/http_local/static/js/ace/keybinding-sublime.js
pyp5js/http_local/static/js/ace/keybinding-vim.js
pyp5js/http_local/static/js/ace/keybinding-vscode.js
pyp5js/http_local/static/js/ace/mode-python.js
pyp5js/http_local/static/js/ace/theme-ambiance.js
pyp5js/http_local/static/js/ace/theme-chaos.js
pyp5js/http_local/static/js/ace/theme-chrome.js
pyp5js/http_local/static/js/ace/theme-clouds.js
pyp5js/http_local/static/js/ace/theme-clouds_midnight.js
pyp5js/http_local/static/js/ace/theme-cobalt.js
pyp5js-0.7.3.dist-info/LICENSE
pyp5js-0.7.3.dist-info/METADATA
pyp5js-0.7.3.dist-info/WHEEL
pyp5js-0.7.3.dist-info/entry_points.txt
pyp5js-0.7.3.dist-info/top_level.txt
pyp5js-0.7.3.dist-info/RECORD
