Metadata-Version: 2.1
Name: pyp5js
Version: 0.7.3
Summary: Simple tool to allow to transcrypt Python code that uses P5.js
Home-page: https://github.com/berinhard/pyp5js/
Author: Bernardo Fontes
Maintainer: Bernardo Fontes
Maintainer-email: bernardoxhc@gmail.com
License: GNU Lesser General Public License version 3
Keywords: p5js processing creative coding
Requires-Python: >=3.6
License-File: LICENSE
Requires-Dist: Click (==8.0.1)
Requires-Dist: Jinja2 (==3.1.2)
Requires-Dist: Transcrypt (==3.9.0)
Requires-Dist: cprint (==1.2.2)
Requires-Dist: gunicorn (==20.1.0)
Requires-Dist: watchdog (==2.1.9)
Requires-Dist: python-decouple (==3.6)
Requires-Dist: Flask (==2.2.2)
Requires-Dist: python-slugify (==6.1.2)
Requires-Dist: markupsafe (==2.1.1)
